chmlfrp_cli/__init__.py
chmlfrp_cli/main.py
chmlfrp_cli-0.1.0.dist-info/entry_points.txt
chmlfrp_cli-0.1.0.dist-info/METADATA
chmlfrp_cli-0.1.0.dist-info/WHEEL
chmlfrp_cli-0.1.0.dist-info/RECORD
