Metadata-Version: 2.3
Name: chmlfrp_cli
Version: 0.1.0
Summary: 用于chmlfrp的cli工具
License: MIT
Author: purilin
Author-email: 2896150207@qq.com
Requires-Python: >=3.11
Classifier: License :: OSI Approved :: MIT License
Classifier: Programming Language :: Python :: 3
Classifier: Programming Language :: Python :: 3.11
Classifier: Programming Language :: Python :: 3.12
Classifier: Programming Language :: Python :: 3.13
Requires-Dist: httpx (>=0.28.1)
Requires-Dist: inquirerpy (>=0.3.4)
Requires-Dist: rich (>=14.0.0)
Requires-Dist: typer (>=0.16.0)
Project-URL: Documentation, https://github.com/drizzlexlh/chmlfrp-cli/#readme
Project-URL: Repository, https://github.com/drizzlexlh/chmlfrp-cli/
